browsergym/visualwebarena/__init__.py
browsergym/visualwebarena/config.py
browsergym/visualwebarena/instance.py
browsergym/visualwebarena/task.py
browsergym/visualwebarena/utils.py
browsergym_visualwebarena-0.14.3.dist-info/METADATA
browsergym_visualwebarena-0.14.3.dist-info/WHEEL
browsergym_visualwebarena-0.14.3.dist-info/RECORD
